{
 "displayFieldName": "Name",
 "fieldAliases": {
  "Name": "Name"
 },
 "geometryType": "esriGeometryPolyline",
 "spatialReference": {
  "wkid": 102100,
  "latestWkid": 3857
 },
 "fields": [
  {
   "name": "Name",
   "type": "esriFieldTypeString",
   "alias": "Name",
   "length": 255
  }
 ],
 "features": [
  {
   "attributes": {
    "Name": "Lakewalk"
   },
   "geometry": {
    "paths": [
     [
      [
       -10252060.7467,
       5906482.2148000002
      ],
      [
       -10252051.2457,
       5906478.0844999999
      ],
      [
       -10251897.5394,
       5906129.3533999994
      ],
      [
       -10251881.5902,
       5906127.3682999983
      ],
      [
       -10251816.241800001,
       5906127.4513999969
      ],
      [
       -10251726.1691,
       5906150.8255999982
      ],
      [
       -10251553.372300001,
       5906233.2709000036
      ],
      [
       -10251625.785,
       5906382.6248999983
      ],
      [
       -10251624.584899999,
       5906411.8395000026
      ],
      [
       -10251621.5964,
       5906468.9116000012
      ],
      [
       -10251657.711200001,
       5906608.0131999999
      ],
      [
       -10251721.396500001,
       5906778.0433000028
      ],
      [
       -10251726.1501,
       5906805.3231000006
      ],
      [
       -10251731.0296,
       5906914.7613999993
      ],
      [
       -10251737.255999999,
       5906974.2853000015
      ],
      [
       -10251748.3719,
       5907017.9161999971
      ],
      [
       -10251788.098099999,
       5907122.8403000012
      ],
      [
       -10251814.907500001,
       5907197.5370000005
      ],
      [
       -10251832.2272,
       5907237.9218999967
      ],
      [
       -10251880.7127,
       5907319.3725000024
      ],
      [
       -10251901.365700001,
       5907354.5998999998
      ],
      [
       -10251912.589199999,
       5907380.9206999987
      ],
      [
       -10251919.520300001,
       5907407.616899997
      ],
      [
       -10251926.3499,
       5907464.8219999969
      ],
      [
       -10251930.249700001,
       5907509.3972000033
      ],
      [
       -10251930.283500001,
       5907528.5658000037
      ],
      [
       -10251922.115700001,
       5907547.9042999968
      ],
      [
       -10251888.976,
       5907588.5991000012
      ],
      [
       -10251698.5167,
       5907809.5768999979
      ],
      [
       -10251676.215299999,
       5907830.1519000009
      ],
      [
       -10251613.932,
       5907869.5622000024
      ],
      [
       -10251598.208000001,
       5907902.7079999968
      ],
      [
       -10251588.2258,
       5907932.6125999987
      ],
      [
       -10251571.7204,
       5907963.0879999995
      ],
      [
       -10251424.341,
       5908213.1623999998
      ]
     ]
    ]
   }
  },
  {
   "attributes": {
    "Name": "Lakewalk"
   },
   "geometry": {
    "paths": [
     [
      [
       -10251804.9377,
       5906573.5350999981
      ],
      [
       -10251668.0384,
       5906635.5852999985
      ]
     ]
    ]
   }
  },
  {
   "attributes": {
    "Name": "Skywalk"
   },
   "geometry": {
    "paths": [
     [
      [
       -10252683.212400001,
       5906998.5116999969
      ],
      [
       -10252785.433900001,
       5907087.6520999968
      ],
      [
       -10252813.5441,
       5907099.8413999975
      ],
      [
       -10252895.9528,
       5907012.5301999971
      ],
      [
       -10252975.254000001,
       5907083.1075000018
      ],
      [
       -10253071.217399999,
       5906976.5380999967
      ],
      [
       -10253063.052200001,
       5906936.8747000024
      ],
      [
       -10253088.2481,
       5906888.3262000009
      ]
     ]
    ]
   }
  },
  {
   "attributes": {
    "Name": "Skywalk"
   },
   "geometry": {
    "paths": [
     [
      [
       -10252661.355599999,
       5906850.6504999995
      ],
      [
       -10252481.0995,
       5906680.4012999982
      ],
      [
       -10252475.2071,
       5906647.9064000025
      ],
      [
       -10252328.4947,
       5906524.8000999987
      ]
     ]
    ]
   }
  },
  {
   "attributes": {
    "Name": "Lakewalk"
   },
   "geometry": {
    "paths": [
     [
      [
       -10252504.877699999,
       5906008.3150999993
      ],
      [
       -10252136.6151,
       5906431.5760999992
      ],
      [
       -10252129.7004,
       5906449.5464999974
      ]
     ]
    ]
   }
  },
  {
   "attributes": {
    "Name": "Lakewalk"
   },
   "geometry": {
    "paths": [
     [
      [
       -10251424.341,
       5908213.1623999998
      ],
      [
       -10251451.364499999,
       5908227.7788000032
      ],
      [
       -10251466.524,
       5908244.5285999998
      ]
     ]
    ]
   }
  },
  {
   "attributes": {
    "Name": "Lakewalk"
   },
   "geometry": {
    "paths": [
     [
      [
       -10251922.7333,
       5907434.5288999975
      ],
      [
       -10251944.9683,
       5907452.2378999963
      ],
      [
       -10251955.473099999,
       5907472.1336999983
      ],
      [
       -10251969.4431,
       5907519.1145000011
      ]
     ]
    ]
   }
  },
  {
   "attributes": {
    "Name": "Lakewalk"
   },
   "geometry": {
    "paths": [
     [
      [
       -10251969.4431,
       5907519.1145000011
      ],
      [
       -10252071.7279,
       5907542.4835999981
      ],
      [
       -10252126.8631,
       5907483.9792999998
      ]
     ]
    ]
   }
  },
  {
   "attributes": {
    "Name": "Lakewalk"
   },
   "geometry": {
    "paths": [
     [
      [
       -10252126.8631,
       5907483.9792999998
      ],
      [
       -10252167.2521,
       5907519.8844999969
      ]
     ]
    ]
   }
  },
  {
   "attributes": {
    "Name": "Lakewalk"
   },
   "geometry": {
    "paths": [
     [
      [
       -10252126.8631,
       5907483.9792999998
      ],
      [
       -10252244.0035,
       5907351.5802000016
      ],
      [
       -10252281.359099999,
       5907382.7493999973
      ]
     ]
    ]
   }
  },
  {
   "attributes": {
    "Name": "Lakewalk"
   },
   "geometry": {
    "paths": [
     [
      [
       -10251969.4431,
       5907519.1145000011
      ],
      [
       -10251948.6094,
       5907543.9430999979
      ],
      [
       -10251657.5284,
       5907892.0405000001
      ],
      [
       -10251640.9279,
       5907921.4287
      ],
      [
       -10251634.3771,
       5907959.249499999
      ],
      [
       -10251635.097100001,
       5907980.0014000013
      ],
      [
       -10251654.489800001,
       5908001.3106999993
      ],
      [
       -10251650.154300001,
       5908026.887000002
      ]
     ]
    ]
   }
  },
  {
   "attributes": {
    "Name": "Lakewalk"
   },
   "geometry": {
    "paths": [
     [
      [
       -10251900.6424,
       5907601.3057999983
      ],
      [
       -10251938.4308,
       5907696.0410000011
      ],
      [
       -10251973.6505,
       5907731.0411000028
      ]
     ]
    ]
   }
  },
  {
   "attributes": {
    "Name": "Skywalk"
   },
   "geometry": {
    "paths": [
     [
      [
       -10252661.355599999,
       5906850.6504999995
      ],
      [
       -10252719.080700001,
       5906785.9724999964
      ],
      [
       -10252778.447000001,
       5906836.6502000019
      ],
      [
       -10252819.7585,
       5906790.3025000021
      ],
      [
       -10252838.4219,
       5906823.1130999997
      ]
     ]
    ]
   }
  },
  {
   "attributes": {
    "Name": "Skywalk"
   },
   "geometry": {
    "paths": [
     [
      [
       -10252792.898700001,
       5906695.9416000023
      ],
      [
       -10252823.525800001,
       5906665.307099998
      ],
      [
       -10252895.632200001,
       5906710.2690000013
      ],
      [
       -10252915.491599999,
       5906727.9692000002
      ]
     ]
    ]
   }
  },
  {
   "attributes": {
    "Name": "Skywalk"
   },
   "geometry": {
    "paths": [
     [
      [
       -10252661.355599999,
       5906850.6504999995
      ],
      [
       -10252646.981000001,
       5906868.8104000017
      ],
      [
       -10252755.7426,
       5906963.5261000022
      ],
      [
       -10252708.4135,
       5907020.4878000021
      ]
     ]
    ]
   }
  },
  {
   "attributes": {
    "Name": "Skywalk"
   },
   "geometry": {
    "paths": [
     [
      [
       -10252683.212400001,
       5906998.5116999969
      ],
      [
       -10252837.816400001,
       5906822.8291999996
      ],
      [
       -10252910.9913,
       5906736.3169
      ],
      [
       -10252918.4814,
       5906725.3324000016
      ],
      [
       -10252940.9396,
       5906745.9039999992
      ],
      [
       -10253116.5702,
       5906539.6828000024
      ]
     ]
    ]
   }
  },
  {
   "attributes": {
    "Name": "Skywalk"
   },
   "geometry": {
    "paths": [
     [
      [
       -10253116.5702,
       5906539.6828000024
      ],
      [
       -10253063.546499999,
       5906491.7366999984
      ]
     ]
    ]
   }
  },
  {
   "attributes": {
    "Name": "Skywalk"
   },
   "geometry": {
    "paths": [
     [
      [
       -10252492.335000001,
       5907046.1359999999
      ],
      [
       -10252502.387599999,
       5907066.6334000006
      ],
      [
       -10252554.265699999,
       5907095.0524000004
      ],
      [
       -10252582.2481,
       5907113.4192000031
      ]
     ]
    ]
   }
  },
  {
   "attributes": {
    "Name": "Skywalk"
   },
   "geometry": {
    "paths": [
     [
      [
       -10252704.894200001,
       5906919.2444000021
      ],
      [
       -10252552.801000001,
       5907096.7619000003
      ]
     ]
    ]
   }
  },
  {
   "attributes": {
    "Name": "Skywalk"
   },
   "geometry": {
    "paths": [
     [
      [
       -10252240.344699999,
       5907421.1568000019
      ],
      [
       -10252277.910499999,
       5907455.1252000034
      ]
     ]
    ]
   }
  },
  {
   "attributes": {
    "Name": "Skywalk"
   },
   "geometry": {
    "paths": [
     [
      [
       -10252324.640900001,
       5907475.9843000025
      ],
      [
       -10252341.9878,
       5907491.7635999992
      ],
      [
       -10252382.884400001,
       5907445.941200003
      ],
      [
       -10252393.7578,
       5907406.7370000035
      ],
      [
       -10252435.615800001,
       5907360.4978
      ],
      [
       -10252393.800000001,
       5907323.5749000013
      ],
      [
       -10252582.2481,
       5907113.4192000031
      ]
     ]
    ]
   }
  },
  {
   "attributes": {
    "Name": "Skywalk"
   },
   "geometry": {
    "paths": [
     [
      [
       -10252582.2481,
       5907113.4192000031
      ],
      [
       -10252683.7498,
       5906998.8266000003
      ]
     ]
    ]
   }
  },
  {
   "attributes": {
    "Name": "Skywalk"
   },
   "geometry": {
    "paths": [
     [
      [
       -10252479.4219,
       5907167.2883000001
      ],
      [
       -10252510.771299999,
       5907193.8037
      ]
     ]
    ]
   }
  },
  {
   "attributes": {
    "Name": "Skywalk"
   },
   "geometry": {
    "paths": [
     [
      [
       -10252427.364700001,
       5907224.5661000013
      ],
      [
       -10252387.2349,
       5907270.3329000026
      ]
     ]
    ]
   }
  },
  {
   "attributes": {
    "Name": "Skywalk"
   },
   "geometry": {
    "paths": [
     [
      [
       -10252437.5933,
       5907272.8422000036
      ],
      [
       -10252408.383300001,
       5907246.2138999999
      ]
     ]
    ]
   }
  },
  {
   "attributes": {
    "Name": "Skywalk"
   },
   "geometry": {
    "paths": [
     [
      [
       -10252081.306700001,
       5908412.8193999976
      ],
      [
       -10252031.589600001,
       5908368.0203000009
      ]
     ]
    ]
   }
  },
  {
   "attributes": {
    "Name": "Skywalk"
   },
   "geometry": {
    "paths": [
     [
      [
       -10251943.794399999,
       5908322.0844999999
      ],
      [
       -10251912.16,
       5908292.4585999995
      ],
      [
       -10251899.696,
       5908284.054399997
      ],
      [
       -10251884.838199999,
       5908278.2135000005
      ],
      [
       -10251872.1884,
       5908278.9350000024
      ],
      [
       -10251860.003599999,
       5908283.6174999997
      ]
     ]
    ]
   }
  },
  {
   "attributes": {
    "Name": "Skywalk"
   },
   "geometry": {
    "paths": [
     [
      [
       -10251815.374299999,
       5908241.487499997
      ],
      [
       -10251777.2897,
       5908208.6673000008
      ]
     ]
    ]
   }
  },
  {
   "attributes": {
    "Name": "Skywalk"
   },
   "geometry": {
    "paths": [
     [
      [
       -10251970.984099999,
       5907911.9231000021
      ],
      [
       -10251988.4186,
       5907884.1032999977
      ],
      [
       -10252024.392000001,
       5907842.6664000005
      ],
      [
       -10252019.983200001,
       5907837.1613999978
      ]
     ]
    ]
   }
  },
  {
   "attributes": {
    "Name": "Skywalk"
   },
   "geometry": {
    "paths": [
     [
      [
       -10251860.7456,
       5908044.3158000037
      ],
      [
       -10251825.2247,
       5908083.6111999974
      ]
     ]
    ]
   }
  },
  {
   "attributes": {
    "Name": "Skywalk"
   },
   "geometry": {
    "paths": [
     [
      [
       -10253338.4516,
       5906861.7290000021
      ],
      [
       -10253291.846899999,
       5906837.4575999975
      ],
      [
       -10253292.2831,
       5906836.9632999972
      ]
     ]
    ]
   }
  }
 ]
}